azure/functions/extension/blob/__init__.py
azure/functions/extension/blob/blobClient.py
azure/functions/extension/blob/blobClientConverter.py
azure/functions/extension/blob/containerClient.py
azure/functions/extension/blob/storageStreamDownloader.py
azure_functions_extension_blob-1.0.0a1.dist-info/LICENSE
azure_functions_extension_blob-1.0.0a1.dist-info/METADATA
azure_functions_extension_blob-1.0.0a1.dist-info/WHEEL
azure_functions_extension_blob-1.0.0a1.dist-info/top_level.txt
azure_functions_extension_blob-1.0.0a1.dist-info/RECORD
