Metadata-Version: 2.1
Name: azure-functions-extension-blob
Version: 1.0.0a1
Summary: Blob Python worker extension for Azure Functions.
Author: Azure Functions team at Microsoft Corp.
Author-email: azurefunctions@microsoft.com
Classifier: Programming Language :: Python :: 3
Classifier: License :: OSI Approved :: MIT License
Classifier: Operating System :: OS Independent
Requires-Python: >=3.7
License-File: LICENSE
Requires-Dist: azure-functions-extension-base
Requires-Dist: azure-storage-blob ==12.19.0
